{
    "parts": {
        "entitynameD0CDD7E0109F4868AACA571AFC5B522D": {
            "clipname1_041FD28D3E6E4C29955FEEA5D39B4969_heightAlign": {
                "alphaFactor": 1,
                "blendmode": 1001,
                "fps": 0,
                "height": 960,
                "textureIdx": {
                    "idx": [
                        0,
                        0,
                        0,
                        1,
                        1,
                        1,
                        2,
                        2,
                        2,
                        3,
                        3,
                        3,
                        4,
                        4,
                        4,
                        5,
                        5,
                        5,
                        6,
                        6,
                        6,
                        7,
                        7,
                        7,
                        8,
                        8,
                        8,
                        9,
                        9,
                        9,
                        10,
                        10,
                        10,
                        11,
                        11,
                        11,
                        12,
                        12,
                        12,
                        13,
                        13,
                        13,
                        14,
                        14,
                        14,
                        15,
                        15,
                        15,
                        16,
                        16,
                        16,
                        17,
                        17,
                        17,
                        18,
                        18,
                        18,
                        19,
                        19,
                        19,
                        20,
                        20,
                        20,
                        21,
                        21,
                        21,
                        22,
                        22,
                        22,
                        23,
                        23,
                        23,
                        24,
                        24,
                        24,
                        25,
                        25,
                        25,
                        26,
                        26,
                        26,
                        27,
                        27,
                        27,
                        28,
                        28,
                        28,
                        29,
                        29,
                        29,
                        30,
                        30,
                        30,
                        31,
                        31,
                        31
                    ],
                    "type": "image"
                },
                "transformParams": {
                    "position": {
                        "point0": {
                                "anchor": [0.5, 0.0],
                                "point": [{
                                        "idx": "topleft",
                                        "relationRef": 0,
                                        "relationType": "foreground",
                                        "weight": 0.5
                                }, {
                                        "idx": "topright",
                                        "relationRef": 0,
                                        "relationType": "foreground",
                                        "weight": 0.5
                                }]
                        },
                        "point1": {
                                "anchor": [0.5, 1.0],
                                "point": [{
                                        "idx": "bottomleft",
                                        "relationRef": 0,
                                        "relationType": "foreground",
                                        "weight": 0.5
                                }, {
                                        "idx": "bottomright",
                                        "relationRef": 0,
                                        "relationType": "foreground",
                                        "weight": 0.5
                                }]
                          }
                    },
                    "relation": {
                        "foreground": 1
                    },
                    "relationIndex": [
                        0
                    ],
                    "relationRefOrder": 0,
                    "rotationtype": 1,
                    "scale": {
                    }
                },
                "transformType": "FOLLOW",
                "width": 540,
                "zorder": 5000
            },
            "clipname1_041FD28D3E6E4C29955FEEA5D39B4969_widthAlign": {
                "alphaFactor": 1,
                "blendmode": 1001,
                "fps": 0,
                "height": 960,
                "textureIdx": {
                    "idx": [
                        0,
                        0,
                        0,
                        1,
                        1,
                        1,
                        2,
                        2,
                        2,
                        3,
                        3,
                        3,
                        4,
                        4,
                        4,
                        5,
                        5,
                        5,
                        6,
                        6,
                        6,
                        7,
                        7,
                        7,
                        8,
                        8,
                        8,
                        9,
                        9,
                        9,
                        10,
                        10,
                        10,
                        11,
                        11,
                        11,
                        12,
                        12,
                        12,
                        13,
                        13,
                        13,
                        14,
                        14,
                        14,
                        15,
                        15,
                        15,
                        16,
                        16,
                        16,
                        17,
                        17,
                        17,
                        18,
                        18,
                        18,
                        19,
                        19,
                        19,
                        20,
                        20,
                        20,
                        21,
                        21,
                        21,
                        22,
                        22,
                        22,
                        23,
                        23,
                        23,
                        24,
                        24,
                        24,
                        25,
                        25,
                        25,
                        26,
                        26,
                        26,
                        27,
                        27,
                        27,
                        28,
                        28,
                        28,
                        29,
                        29,
                        29,
                        30,
                        30,
                        30,
                        31,
                        31,
                        31
                    ],
                    "type": "image"
                },
                "transformParams": {
                    "position": {
                        "point0": {
                                "anchor": [0.0, 0.5],
                                "point": [{
                                        "idx": "topleft",
                                        "relationRef": 0,
                                        "relationType": "foreground",
                                        "weight": 0.5
                                }, {
                                        "idx": "bottomleft",
                                        "relationRef": 0,
                                        "relationType": "foreground",
                                        "weight": 0.5
                                }]
                        },
                        "point1": {
                                "anchor": [1.0, 0.5],
                                "point": [{
                                        "idx": "topright",
                                        "relationRef": 0,
                                        "relationType": "foreground",
                                        "weight": 0.5
                                }, {
                                        "idx": "bottomright",
                                        "relationRef": 0,
                                        "relationType": "foreground",
                                        "weight": 0.5
                                }]
                        }
                    },
                    "relation": {
                        "foreground": 1
                    },
                    "relationIndex": [
                        0
                    ],
                    "relationRefOrder": 0,
                    "rotationtype": 1,
                    "scale": {
                    }
                },
                "transformType": "FOLLOW",
                "width": 540,
                "zorder": 5000
            }
        }
    },
    "texturefiles": [
        "ribvjkmp_1551079700/ribvjkmp_1551079700_000.png",
        "ribvjkmp_1551079700/ribvjkmp_1551079700_001.png",
        "ribvjkmp_1551079700/ribvjkmp_1551079700_002.png",
        "ribvjkmp_1551079700/ribvjkmp_1551079700_003.png",
        "ribvjkmp_1551079700/ribvjkmp_1551079700_004.png",
        "ribvjkmp_1551079700/ribvjkmp_1551079700_005.png",
        "ribvjkmp_1551079700/ribvjkmp_1551079700_006.png",
        "ribvjkmp_1551079700/ribvjkmp_1551079700_007.png",
        "ribvjkmp_1551079700/ribvjkmp_1551079700_008.png",
        "ribvjkmp_1551079700/ribvjkmp_1551079700_009.png",
        "ribvjkmp_1551079700/ribvjkmp_1551079700_010.png",
        "ribvjkmp_1551079700/ribvjkmp_1551079700_011.png",
        "ribvjkmp_1551079700/ribvjkmp_1551079700_012.png",
        "ribvjkmp_1551079700/ribvjkmp_1551079700_013.png",
        "ribvjkmp_1551079700/ribvjkmp_1551079700_014.png",
        "ribvjkmp_1551079700/ribvjkmp_1551079700_015.png",
        "ribvjkmp_1551079700/ribvjkmp_1551079700_016.png",
        "ribvjkmp_1551079700/ribvjkmp_1551079700_017.png",
        "ribvjkmp_1551079700/ribvjkmp_1551079700_018.png",
        "ribvjkmp_1551079700/ribvjkmp_1551079700_019.png",
        "ribvjkmp_1551079700/ribvjkmp_1551079700_020.png",
        "ribvjkmp_1551079700/ribvjkmp_1551079700_021.png",
        "ribvjkmp_1551079700/ribvjkmp_1551079700_022.png",
        "ribvjkmp_1551079700/ribvjkmp_1551079700_023.png",
        "ribvjkmp_1551079700/ribvjkmp_1551079700_024.png",
        "ribvjkmp_1551079700/ribvjkmp_1551079700_025.png",
        "ribvjkmp_1551079700/ribvjkmp_1551079700_026.png",
        "ribvjkmp_1551079700/ribvjkmp_1551079700_027.png",
        "ribvjkmp_1551079700/ribvjkmp_1551079700_028.png",
        "ribvjkmp_1551079700/ribvjkmp_1551079700_029.png",
        "ribvjkmp_1551079700/ribvjkmp_1551079700_030.png",
        "ribvjkmp_1551079700/ribvjkmp_1551079700_031.png"
    ],
    "version": "2.9.1"
}